README.md
setup.py
protobuf_converter/__init__.py
protobuf_converter/converter.py
protobuf_converter.egg-info/PKG-INFO
protobuf_converter.egg-info/SOURCES.txt
protobuf_converter.egg-info/dependency_links.txt
protobuf_converter.egg-info/requires.txt
protobuf_converter.egg-info/top_level.txt
protobuf_converter/tests/__init__.py
protobuf_converter/tests/sample_pb2.py
protobuf_converter/tests/test_proto_to_dict.py